odoo/addons/resource_booking/README.rst
odoo/addons/resource_booking/__init__.py
odoo/addons/resource_booking/__manifest__.py
odoo/addons/resource_booking/hooks.py
odoo/addons/resource_booking/controllers/__init__.py
odoo/addons/resource_booking/controllers/portal.py
odoo/addons/resource_booking/data/mail.xml
odoo/addons/resource_booking/data/mail_data.xml
odoo/addons/resource_booking/demo/res_users_demo.xml
odoo/addons/resource_booking/demo/resource_booking_type_demo.xml
odoo/addons/resource_booking/demo/resource_combination_demo.xml
odoo/addons/resource_booking/demo/resource_resource_demo.xml
odoo/addons/resource_booking/i18n/ca.po
odoo/addons/resource_booking/i18n/es.po
odoo/addons/resource_booking/i18n/fr.po
odoo/addons/resource_booking/i18n/fr_FR.po
odoo/addons/resource_booking/i18n/it.po
odoo/addons/resource_booking/i18n/pt_BR.po
odoo/addons/resource_booking/i18n/resource_booking.pot
odoo/addons/resource_booking/models/__init__.py
odoo/addons/resource_booking/models/calendar_event.py
odoo/addons/resource_booking/models/mail_activity.py
odoo/addons/resource_booking/models/res_partner.py
odoo/addons/resource_booking/models/resource_booking.py
odoo/addons/resource_booking/models/resource_booking_combination.py
odoo/addons/resource_booking/models/resource_booking_type.py
odoo/addons/resource_booking/models/resource_booking_type_combination_rel.py
odoo/addons/resource_booking/models/resource_calendar.py
odoo/addons/resource_booking/models/resource_resource.py
odoo/addons/resource_booking/readme/CONFIGURE.md
odoo/addons/resource_booking/readme/CONTRIBUTORS.md
odoo/addons/resource_booking/readme/DESCRIPTION.md
odoo/addons/resource_booking/readme/INSTALL.md
odoo/addons/resource_booking/readme/ROADMAP.md
odoo/addons/resource_booking/readme/USAGE.md
odoo/addons/resource_booking/security/ir.model.access.csv
odoo/addons/resource_booking/security/resource_booking_security.xml
odoo/addons/resource_booking/static/description/icon.png
odoo_addon_resource_booking-18.0.1.0.9.dist-info/METADATA
odoo_addon_resource_booking-18.0.1.0.9.dist-info/WHEEL
odoo_addon_resource_booking-18.0.1.0.9.dist-info/top_level.txt
odoo_addon_resource_booking-18.0.1.0.9.dist-info/RECORD
