Metadata-Version: 2.1
Name: odoo-addon-resource_booking
Version: 18.0.1.0.9
Requires-Python: >=3.10
Requires-Dist: cssselect
Requires-Dist: odoo-addon-web_calendar_slot_duration==18.0.*
Requires-Dist: odoo==18.0.*
Summary: Manage appointments and resource booking
Home-page: https://github.com/OCA/calendar
License: AGPL-3
Author: Tecnativa, Odoo Community Association (OCA)
Author-email: support@odoo-community.org
Classifier: Programming Language :: Python
Classifier: Framework :: Odoo
Classifier: Framework :: Odoo :: 18.0
Classifier: License :: OSI Approved :: GNU Affero General Public License v3
Classifier: Development Status :: 5 - Production/Stable
